pysetimexif.py
pysetimexif-1.0.2.dist-info/entry_points.txt
pysetimexif-1.0.2.dist-info/licenses/LICENSE.txt
pysetimexif-1.0.2.dist-info/WHEEL
pysetimexif-1.0.2.dist-info/METADATA
pysetimexif-1.0.2.dist-info/RECORD
