Metadata-Version: 2.4
Name: pysetimexif
Version: 1.0.2
Summary: Tool for setting 'modified timestamp' on files according to their EXIF information.
Author-email: Erik Petersen <eht@it-trans.dk>
Requires-Python: >=3.6
Classifier: Programming Language :: Python :: 3
Classifier: License :: OSI Approved :: MIT License
Classifier: Operating System :: OS Independent
License-File: LICENSE.txt
Requires-Dist: ExifRead
Project-URL: Home, https://github.com/epetersen-lab/pysetimexif
